Metadata-Version: 2.1
Name: django-admin-lazy-load
Version: 0.2.1
Summary: Allows to speed-up loading of django admin page by loading heavy calculated field in lazy maner - via separate ajax requests.
Home-page: https://github.com/mihasK/django-admin-lazy-load
Author: mihasK
License: GNU General Public License v3.0
Platform: UNKNOWN
Classifier: Environment :: Web Environment
Classifier: Framework :: Django
Classifier: Framework :: Django :: 2.2
Classifier: Intended Audience :: Developers
Classifier: License :: OSI Approved :: GNU General Public License v3 (GPLv3)
Classifier: Operating System :: OS Independent
Classifier: Programming Language :: Python
Classifier: Programming Language :: Python :: 3
License-File: LICENSE
